randre.py
randre-0.1.0.dist-info/LICENSE.txt
randre-0.1.0.dist-info/METADATA
randre-0.1.0.dist-info/RECORD
randre-0.1.0.dist-info/WHEEL
randre-0.1.0.dist-info/top_level.txt
