Metadata-Version: 2.1
Name: randre
Version: 0.1.0
Summary: Generate random text from regular expression patterns
Home-page: https://github.com/sorcio/randre
Author: Davide Rizzo
Author-email: sorcio@gmail.com
License: UNKNOWN
Platform: UNKNOWN
Classifier: Development Status :: 2 - Pre-Alpha
Classifier: License :: OSI Approved :: BSD License
Classifier: Programming Language :: Python :: 3
Classifier: Programming Language :: Python :: 3.4
Classifier: Programming Language :: Python :: 3.5
Classifier: Programming Language :: Python :: 3.6
Requires-Python: >=3
